triz2DAAD/__init__.py
triz2DAAD/triz2DAAD.py
triz2DAAD-1.0.4b8.dist-info/LICENSE
triz2DAAD-1.0.4b8.dist-info/METADATA
triz2DAAD-1.0.4b8.dist-info/WHEEL
triz2DAAD-1.0.4b8.dist-info/top_level.txt
triz2DAAD-1.0.4b8.dist-info/RECORD
