Metadata-Version: 2.1
Name: triz2DAAD
Version: 1.0.4b8
Summary: Convierte mapas de aventuras de texto generados por Trizbort en código fuente para el DAAD.
Author-email: Pedro Fernández <rockersuke@gmail.com>
Project-URL: Homepage, https://zonafi.es/triz2DAAD/
Classifier: Programming Language :: Python :: 3
Classifier: License :: OSI Approved :: MIT License
Classifier: Operating System :: OS Independent
Requires-Python: >=3.7
License-File: LICENSE
